tialgo/__init__.py
tialgo/table_data_model.py
tialgo-0.0.2.dist-info/METADATA
tialgo-0.0.2.dist-info/WHEEL
tialgo-0.0.2.dist-info/top_level.txt
tialgo-0.0.2.dist-info/RECORD
