Metadata-Version: 2.1
Name: tialgo
Version: 0.0.2
Summary: Algorithm SDK for TencentCloud TIONE
Home-page: https://cloud.tencent.com
Author: liang chen
Author-email: chenliang@tencent.com
License: MIT
Platform: UNKNOWN
Classifier: License :: OSI Approved :: MIT License
Classifier: Programming Language :: Python :: 3
Classifier: Programming Language :: Python :: 3.7
Requires-Dist: pandas
Requires-Dist: matplotlib
Requires-Dist: numpy
